<annotation>
  <folder></folder>
  <filename>hvt3.png</filename>
  <source>
    <database>Unknown</database>
    <annotation>Unknown</annotation>
    <image>Unknown</image>
  </source>
  <size>
    <width>936</width>
    <height>517</height>
    <depth></depth>
  </size>
  <segmented>0</segmented>
  <object>
    <name>HVT1</name>
    <truncated>0</truncated>
    <occluded>0</occluded>
    <difficult>0</difficult>
    <bndbox>
      <xmin>290.09</xmin>
      <ymin>169.96</ymin>
      <xmax>343.95</xmax>
      <ymax>238.36</ymax>
    </bndbox>
    <attributes>
      <attribute>
        <name>rotation</name>
        <value>0.0</value>
      </attribute>
    </attributes>
  </object>
  <object>
    <name>HVT1</name>
    <truncated>0</truncated>
    <occluded>0</occluded>
    <difficult>0</difficult>
    <bndbox>
      <xmin>615.29</xmin>
      <ymin>173.89</ymin>
      <xmax>670.01</xmax>
      <ymax>239.3</ymax>
    </bndbox>
    <attributes>
      <attribute>
        <name>rotation</name>
        <value>0.0</value>
      </attribute>
    </attributes>
  </object>
</annotation>
